logis/__init__.py
logis/_i18n/__init__.py
logis/_i18n/locales/__init__.py
logis/_log/__init__.py
logis/_log/builder.py
logis/_log/fmt.py
logis/_log/handler.py
logis/_log/util.py
logis/_log/model/__init__.py
logis/_log/model/dict_config.py
logis/alg/__init__.py
logis/alg/path_finding/__init__.py
logis/alg/path_finding/model/__init__.py
logis/biz/__init__.py
logis/biz/sim/__init__.py
logis/biz/sim/iface/__init__.py
logis/biz/sim/iface/order.py
logis/biz/sim/iface/picking.py
logis/biz/sim/iface/wave.py
logis/conf/__init__.py
logis/ctx/__init__.py
logis/data_type/__init__.py
logis/data_type/_math.py
logis/data_type/base.py
logis/data_type/echarts.py
logis/data_type/exception.py
logis/data_type/net.py
logis/data_type/notice.py
logis/data_type/page.py
logis/data_type/point.py
logis/data_type/spatial.py
logis/data_type/unitable.py
logis/decorator/__init__.py
logis/event/__init__.py
logis/iface/__init__.py
logis/iface/_event.py
logis/iface/_queue.py
logis/iface/container.py
logis/iface/handler.py
logis/iface/lifecycle.py
logis/metric/__init__.py
logis/metric/influxdb/__init__.py
logis/mq/__init__.py
logis/mq/_zmq.py
logis/patch/__init__.py
logis/patch/_random.py
logis/task/__init__.py
logis/task/manager.py
logis/task/iface/__init__.py
logis/task/model/__init__.py
logis/util/__init__.py
logis/util/date_util.py
logis/util/db_util.py
logis/util/dict_util.py
logis/util/echarts_util.py
logis/util/fastapi_util.py
logis/util/io_util.py
logis/util/lambda_util.py
logis/util/math_util.py
logis/util/network_util.py
logis/util/num_util.py
logis/util/obj_util.py
logis/util/os_util.py
logis/util/path_util.py
logis/util/pkg_util.py
logis/util/pydantic_util.py
logis/util/simpy_util.py
logis/util/table_util.py
logis/util/visual_util.py
logis/util/websocket_util.py
logis_sdk-0.1.12.dist-info/licenses/LICENSE
tests/__init__.py
tests/copy_test.py
tests/ctx_test.py
tests/data_type_test.py
tests/diagram_test.py
tests/dict_test.py
tests/echarts_test.py
tests/except_test.py
tests/iface_test.py
tests/influxdb_test.py
tests/io_test.py
logis_sdk-0.1.12.dist-info/METADATA
logis_sdk-0.1.12.dist-info/WHEEL
logis_sdk-0.1.12.dist-info/top_level.txt
logis_sdk-0.1.12.dist-info/RECORD
