Metadata-Version: 2.4
Name: logis-sdk
Version: 0.1.12
Summary: 络捷斯特 Python 模块合集
Author: leoking
Author-email: present150608@sina.com
Requires-Python: >=3.8
License-File: LICENSE
Dynamic: author
Dynamic: author-email
Dynamic: description
Dynamic: description-content-type
Dynamic: license-file
Dynamic: requires-python
Dynamic: summary
